Workbook

Sheet Gastos Ordinarios Mes a Mes
A1: Fecha | B1: Mes | C1: Descripcion | D1: ID | E1: Concepto | F1: Monto Bs | G1: Monto $ | H1: Tasa | I1: Columna1
A2: 46235 | B2: =TEXT(Tabla1[[#This Row],[Fecha ]],"MMMM") -> August | C2: TRABAJO DESTAPE DE CAÑERIA RUBEN PLOMERO | D2: 9 | E2: =IFERROR(VLOOKUP(D:D,'AUXILIAR DE CLASIFICACION'!A:B,2,FALSE),"") -> Gastos Extraordinarios | F2: 37439.32 | G2: =IFERROR(F2/H2,0) -> 50.144409 | H2: 746.63
A3: 46235 | B3: =TEXT(Tabla1[[#This Row],[Fecha ]],"MMMM") -> August | C3: CONTINUACION DE DESTAPE DE CAÑERIA RUBEN PLOMERO | D3: 9 | E3: =IFERROR(VLOOKUP(D:D,'AUXILIAR DE CLASIFICACION'!A:B,2,FALSE),"") -> Gastos Extraordinarios | F3: 37439.32 | G3: =IFERROR(F3/H3,0) -> 50.144409 | H3: 746.63
A4: 46235 | B4: =TEXT(Tabla1[[#This Row],[Fecha ]],"MMMM") -> August | C4: COMPRA DE MATERIALES DESTAPE DE CAÑERIA | D4: 9 | E4: =IFERROR(VLOOKUP(D:D,'AUXILIAR DE CLASIFICACION'!A:B,2,FALSE),"") -> Gastos Extraordinarios | F4: 130806 | G4: =IFERROR(F4/H4,0) -> 175.19521 | H4: 746.63
A5: 46235 | B5: =TEXT(Tabla1[[#This Row],[Fecha ]],"MMMM") -> August | C5: COMPRA DE COMIDA DESTAPE DE CAÑERIA DANIEL ZABALA | D5: 9 | E5: =IFERROR(VLOOKUP(D:D,'AUXILIAR DE CLASIFICACION'!A:B,2,FALSE),"") -> Gastos Extraordinarios | F5: 13500 | G5: =IFERROR(F5/H5,0) -> 18.081245 | H5: 746.63
A6: 46235 | B6: =TEXT(Tabla1[[#This Row],[Fecha ]],"MMMM") -> August | C6: PAGO DE FACTURA DIGITEL | D6: 4 | E6: =IFERROR(VLOOKUP(D:D,'AUXILIAR DE CLASIFICACION'!A:B,2,FALSE),"") -> Servicios | F6: 21806.68 | G6: 24.84 | H6: 756.71
A7: 46237 | B7: =TEXT(Tabla1[[#This Row],[Fecha ]],"MMMM") -> August | C7: HONORARIOS CONTRATO DE ARRENDAMIENTO | D7: 9 | E7: =IFERROR(VLOOKUP(D:D,'AUXILIAR DE CLASIFICACION'!A:B,2,FALSE),"") -> Gastos Extraordinarios | F7: 172238 | G7: =IFERROR(F7/H7,0) -> 200 | H7: 861.19
A8: 46237 | B8: =TEXT(Tabla1[[#This Row],[Fecha ]],"MMMM") -> August | C8: COMPLEMENTO TRABAJO DESTAPE DE CAÑERIA | D8: 9 | E8: =IFERROR(VLOOKUP(D:D,'AUXILIAR DE CLASIFICACION'!A:B,2,FALSE),"") -> Gastos Extraordinarios | F8: 359414.4 | G8: =IFERROR(F8/H8,0) -> 480 | H8: 748.78
A9: 46238 | B9: =TEXT(Tabla1[[#This Row],[Fecha ]],"MMMM") -> August | C9: LIQUIDACION RENUNCIA DANIEL CARRILLO | D9: 7 | E9: =IFERROR(VLOOKUP(D:D,'AUXILIAR DE CLASIFICACION'!A:B,2,FALSE),"") -> Nomina y Pasivos Laborales | F9: 73400 | G9: =IFERROR(F9/H9,0) -> 97.594703 | H9: 752.09
A10: 46238 | B10: =TEXT(Tabla1[[#This Row],[Fecha ]],"MMMM") -> August | C10: REPARACION DE LAMINA DE DRYWALL PASILLO CAÑERIA | D10: 9 | E10: =IFERROR(VLOOKUP(D:D,'AUXILIAR DE CLASIFICACION'!A:B,2,FALSE),"") -> Gastos Extraordinarios | F10: 23388 | G10: =IFERROR(F10/H10,0) -> 31.097342 | H10: 752.09
A11: 46238 | B11: =TEXT(Tabla1[[#This Row],[Fecha ]],"MMMM") -> August | C11: COMPRA GLOBOS CUMPLEAÑOS YURIMA | D11: 9 | E11: =IFERROR(VLOOKUP(D:D,'AUXILIAR DE CLASIFICACION'!A:B,2,FALSE),"") -> Gastos Extraordinarios | F11: 6975.55 | G11: =IFERROR(F11/H11,0) -> 9.2748873 | H11: 752.09
A12: 46238 | B12: =TEXT(Tabla1[[#This Row],[Fecha ]],"MMMM") -> August | C12: GASOLINA PANEL DANIEL RODRIGUEZ | D12: 12 | E12: =IFERROR(VLOOKUP(D:D,'AUXILIAR DE CLASIFICACION'!A:B,2,FALSE),"") -> Mantenimiento Flota | F12: 15041.8 | G12: =IFERROR(F12/H12,0) -> 20 | H12: 752.09
A13: 46238 | B13: =TEXT(Tabla1[[#This Row],[Fecha ]],"MMMM") -> August | C13: COMPRA DE SNACK Y REFRESCOS CUMPLEAÑOS SRA YURIMA | D13: 9 | E13: =IFERROR(VLOOKUP(D:D,'AUXILIAR DE CLASIFICACION'!A:B,2,FALSE),"") -> Gastos Extraordinarios | F13: 9589.06 | G13: =IFERROR(F13/H13,0) -> 12.749884 | H13: 752.09
A14: 46239 | B14: =TEXT(Tabla1[[#This Row],[Fecha ]],"MMMM") -> August | C14: COMPRA CUADERNO ALMACEN | D14: 9 | E14: =IFERROR(VLOOKUP(D:D,'AUXILIAR DE CLASIFICACION'!A:B,2,FALSE),"") -> Gastos Extraordinarios | F14: 3370 | G14: =IFERROR(F14/H14,0) -> 4.4808467 | H14: 752.09
A15: 46239 | B15: =TEXT(Tabla1[[#This Row],[Fecha ]],"MMMM") -> August | C15: COMISION POR VENTA SEMAN 27/7/26 AL 01/8/26 | D15: 8 | E15: =IFERROR(VLOOKUP(D:D,'AUXILIAR DE CLASIFICACION'!A:B,2,FALSE),"") -> Comisiones por venta | F15: 108977.13 | G15: =IFERROR(F15/H15,0) -> 144.30999 | H15: 755.16
A16: 46240 | B16: =TEXT(Tabla1[[#This Row],[Fecha ]],"MMMM") -> August | C16: PAGO TORTA CUMPLEAÑOS DE YURIMA | D16: 9 | E16: =IFERROR(VLOOKUP(D:D,'AUXILIAR DE CLASIFICACION'!A:B,2,FALSE),"") -> Gastos Extraordinarios | F16: 34913.6 | G16: =IFERROR(F16/H16,0) -> 40.000458 | H16: 872.83
A17: 46241 | B17: =TEXT(Tabla1[[#This Row],[Fecha ]],"MMMM") -> August | C17: LIQUIDACION DOMINGO FIGUEROA | D17: 7 | E17: =IFERROR(VLOOKUP(D:D,'AUXILIAR DE CLASIFICACION'!A:B,2,FALSE),"") -> Nomina y Pasivos Laborales | F17: 66585.89 | G17: =IFERROR(F17/H17,0) -> 87.993934 | H17: 756.71
A18: 46241 | B18: =TEXT(Tabla1[[#This Row],[Fecha ]],"MMMM") -> August | C18: COMPRA DE CESTAS NEGRAS PARA ALMACEN 10 UND | D18: 9 | E18: =IFERROR(VLOOKUP(D:D,'AUXILIAR DE CLASIFICACION'!A:B,2,FALSE),"") -> Gastos Extraordinarios | F18: 26156.7 | G18: =IFERROR(F18/H18,0) -> 30 | H18: 871.89
... A20: 46241 | B20: =TEXT(Tabla1[[#This Row],[Fecha ]],"MMMM") -> August | C20: DOS DIAS DE TRABAJO Y APERTURA DANIEL ZABALA | D20: 9 | E20: =IFERROR(VLOOKUP(D:D,'AUXILIAR DE CLASIFICACION'!A:B,2,FALSE),"") -> Gastos Extraordinarios | F20: 249714.3 | G20: =IFERROR(F20/H20,0) -> 330 | H20: 756.71
A21: 46241 | B21: =TEXT(Tabla1[[#This Row],[Fecha ]],"MMMM") -> August | C21: PAGO FACTURA NET UNO | D21: 4 | E21: =IFERROR(VLOOKUP(D:D,'AUXILIAR DE CLASIFICACION'!A:B,2,FALSE),"") -> Servicios | F21: 42793.59 | G21: 56.03 | H21: 748.7864
A22: 46242 | B22: =TEXT(Tabla1[[#This Row],[Fecha ]],"MMMM") -> August | C22: COMPRA DE CAFÉ Y AZUCAR PORA TIENDA | D22: 9 | E22: =IFERROR(VLOOKUP(D:D,'AUXILIAR DE CLASIFICACION'!A:B,2,FALSE),"") -> Gastos Extraordinarios | F22: 39114.24 | G22: =IFERROR(F22/H22,0) -> 51.689868 | H22: 756.71
A23: 46244 | B23: =TEXT(Tabla1[[#This Row],[Fecha ]],"MMMM") -> August | C23: GASOLINA PANEL DANIEL RODRIGUEZ | D23: 12 | E23: =IFERROR(VLOOKUP(D:D,'AUXILIAR DE CLASIFICACION'!A:B,2,FALSE),"") -> Mantenimiento Flota | F23: 15150.8 | G23: =IFERROR(F23/H23,0) -> 20 | H23: 757.54
A24: 46244 | B24: =TEXT(Tabla1[[#This Row],[Fecha ]],"MMMM") -> August | C24: COMISION POR VENTA SEMAN 03/8/26 AL 8/8/26 | D24: 8 | E24: =IFERROR(VLOOKUP(D:D,'AUXILIAR DE CLASIFICACION'!A:B,2,FALSE),"") -> Comisiones por venta | F24: 184036.76 | G24: =IFERROR(F24/H24,0) -> 242.93999 | H24: 757.54
A25: 46244 | B25: =TEXT(Tabla1[[#This Row],[Fecha ]],"MMMM") -> August | C25: RENOVACION LICENCIA ALCADIA ANUAL | D25: 2 | E25: =IFERROR(VLOOKUP(D:D,'AUXILIAR DE CLASIFICACION'!A:B,2,FALSE),"") -> Impuestos Municipales | F25: 2604.92 | G25: =IFERROR(F25/H25,0) -> 3.4386567 | H25: 757.54
A26: 46244 | B26: =TEXT(Tabla1[[#This Row],[Fecha ]],"MMMM") -> August | C26: PAGO DE FACTURA GRUPO CASHEA | D26: 4 | E26: =IFERROR(VLOOKUP(D:D,'AUXILIAR DE CLASIFICACION'!A:B,2,FALSE),"") -> Servicios | F26: 15385.23 | G26: 19.586207 | H26: 755.1552
A27: 46245 | B27: =TEXT(Tabla1[[#This Row],[Fecha ]],"MMMM") -> August | C27: PAGO FACTURA PEGAZO SUMINISTROS PAPELERIA | D27: 9 | E27: =IFERROR(VLOOKUP(D:D,'AUXILIAR DE CLASIFICACION'!A:B,2,FALSE),"") -> Gastos Extraordinarios | F27: 79166.88 | G27: 100 | H27: 761.22
A28: 46246 | B28: =TEXT(Tabla1[[#This Row],[Fecha ]],"MMMM") -> August | C28: PAGO HIDROCENTO JULIO 2026 | D28: 4 | E28: =IFERROR(VLOOKUP(D:D,'AUXILIAR DE CLASIFICACION'!A:B,2,FALSE),"") -> Servicios | F28: 38150.45 | G28: =IFERROR(F28/H28,0) -> 49.912278 | H28: 764.35
A29: 46246 | B29: =TEXT(Tabla1[[#This Row],[Fecha ]],"MMMM") -> August | C29: GASOLINA PANEL DANIEL RODRIGUEZ | D29: 12 | E29: =IFERROR(VLOOKUP(D:D,'AUXILIAR DE CLASIFICACION'!A:B,2,FALSE),"") -> Mantenimiento Flota | F29: 15287 | G29: =IFERROR(F29/H29,0) -> 20 | H29: 764.35
A30: 46247 | B30: =TEXT(Tabla1[[#This Row],[Fecha ]],"MMMM") -> August | C30: PAGO MERCADO LIBRE AGOSTO 2026 | D30: 4 | E30: =IFERROR(VLOOKUP(D:D,'AUXILIAR DE CLASIFICACION'!A:B,2,FALSE),"") -> Servicios | F30: 19592.84 | G30: =IFERROR(F30/H30,0) -> 25.549435 | H30: 766.86
A31: 46247 | B31: =TEXT(Tabla1[[#This Row],[Fecha ]],"MMMM") -> August | C31: BONIFICACION ESPECIAL ORIANNA MONTILLA JULIO 2026 | D31: 9 | E31: =IFERROR(VLOOKUP(D:D,'AUXILIAR DE CLASIFICACION'!A:B,2,FALSE),"") -> Gastos Extraordinarios | F31: 84354.6 | G31: =IFERROR(F31/H31,0) -> 110 | H31: 766.86
A32: 46247 | B32: =TEXT(Tabla1[[#This Row],[Fecha ]],"MMMM") -> August | C32: BONIFICACION ESPECIAL YURIMA RAUSEO JULIO 2026 | D32: 9 | E32: =IFERROR(VLOOKUP(D:D,'AUXILIAR DE CLASIFICACION'!A:B,2,FALSE),"") -> Gastos Extraordinarios | F32: 115029 | G32: =IFERROR(F32/H32,0) -> 150 | H32: 766.86
A33: 46248 | B33: =TEXT(Tabla1[[#This Row],[Fecha ]],"MMMM") -> August | C33: PAGO DE NOMINA PRIMERA QUINCENA AGOSTO 15/8/26 | D33: 7 | E33: =IFERROR(VLOOKUP(D:D,'AUXILIAR DE CLASIFICACION'!A:B,2,FALSE),"") -> Nomina y Pasivos Laborales | F33: 1127120 | G33: =IFERROR(F33/H33,0) -> 1458.9606 | H33: 772.55
A34: 46248 | B34: =TEXT(Tabla1[[#This Row],[Fecha ]],"MMMM") -> August | C34: PAGO DE PEAJE VIAJE CABLESCA | D34: 12 | E34: =IFERROR(VLOOKUP(D:D,'AUXILIAR DE CLASIFICACION'!A:B,2,FALSE),"") -> Mantenimiento Flota | F34: 1000 | G34: =IFERROR(F34/H34,0) -> 1.2968991 | H34: 771.07
A35: 46248 | B35: =TEXT(Tabla1[[#This Row],[Fecha ]],"MMMM") -> August | C35: PAGO DE FLETE N° 2983 TRANSPORTE HERZALES | D35: 9 | E35: =IFERROR(VLOOKUP(D:D,'AUXILIAR DE CLASIFICACION'!A:B,2,FALSE),"") -> Gastos Extraordinarios | F35: 11566.05 | G35: =IFERROR(F35/H35,0) -> 15 | H35: 771.07
A36: 46248 | B36: =TEXT(Tabla1[[#This Row],[Fecha ]],"MMMM") -> August | C36: COMPRA DE TERMO DE CAFÉ CLIENTES | D36: 9 | E36: =IFERROR(VLOOKUP(D:D,'AUXILIAR DE CLASIFICACION'!A:B,2,FALSE),"") -> Gastos Extraordinarios | F36: 17724.25 | G36: =IFERROR(F36/H36,0) -> 22.986564 | H36: 771.07
A37: 46248 | B37: =TEXT(Tabla1[[#This Row],[Fecha ]],"MMMM") -> August | C37: SEGUNDA COMPRA DE CESTAS NEGRAS ALMACEN 10 UND | D37: 9 | E37: =IFERROR(VLOOKUP(D:D,'AUXILIAR DE CLASIFICACION'!A:B,2,FALSE),"") -> Gastos Extraordinarios | F37: 53367 | G37: =IFERROR(F37/H37,0) -> 60 | H37: 889.45
A38: 46248 | B38: =TEXT(Tabla1[[#This Row],[Fecha ]],"MMMM") -> August | C38: TRABAJOS REALIZADOS DANIEL ZABALA | D38: 9 | E38: =IFERROR(VLOOKUP(D:D,'AUXILIAR DE CLASIFICACION'!A:B,2,FALSE),"") -> Gastos Extraordinarios | F38: 239031.7 | G38: =IFERROR(F38/H38,0) -> 310.02412 | H38: 771.01
A39: 46251 | B39: =TEXT(Tabla1[[#This Row],[Fecha ]],"MMMM") -> August | C39: GASOLINA PANEL DANIEL RODRIGUEZ | D39: 12 | E39: =IFERROR(VLOOKUP(D:D,'AUXILIAR DE CLASIFICACION'!A:B,2,FALSE),"") -> Mantenimiento Flota | F39: 15450.8 | G39: =IFERROR(F39/H39,0) -> 19.999741 | H39: 772.55
... A45: 46254 | B45: =TEXT(Tabla1[[#This Row],[Fecha ]],"MMMM") -> August | C45: GASOLINA PANEL DANIEL RODRIGUEZ | D45: 12 | E45: =IFERROR(VLOOKUP(D:D,'AUXILIAR DE CLASIFICACION'!A:B,2,FALSE),"") -> Mantenimiento Flota | F45: 15548 | G45: =IFERROR(F45/H45,0) -> 19.999485 | H45: 777.42
A46: 46254 | B46: =TEXT(Tabla1[[#This Row],[Fecha ]],"MMMM") -> August | C46: PRIMERA CUOTA DE POLIZA CONTRA INCENDIO TEV | D46: 4 | E46: =IFERROR(VLOOKUP(D:D,'AUXILIAR DE CLASIFICACION'!A:B,2,FALSE),"") -> Servicios | F46: =249846.97+1617.3 -> 251464.27 | G46: =IFERROR(F46/H46,0) -> 323.46 | H46: 777.42
A47: 46245 | B47: =TEXT(Tabla1[[#This Row],[Fecha ]],"MMMM") -> August | C47: PAGO DE FACTURA SERVITEPUY DOMINIO DE PAGINA WEB | D47: 4 | E47: =IFERROR(VLOOKUP(D:D,'AUXILIAR DE CLASIFICACION'!A:B,2,FALSE),"") -> Servicios | F47: 58993.57 | G47: 74.517241 | H47: 761.22
A48: 46245 | B48: =TEXT(Tabla1[[#This Row],[Fecha ]],"MMMM") -> August | C48: PAGO DE FACTURA SERVITEPUY RENOVACION DE PAGINA WEB | D48: 4 | E48: =IFERROR(VLOOKUP(D:D,'AUXILIAR DE CLASIFICACION'!A:B,2,FALSE),"") -> Servicios | F48: 21657.77 | G48: 27.353448 | H48: 761.22
A49: 46246 | B49: =TEXT(Tabla1[[#This Row],[Fecha ]],"MMMM") -> August | C49: PRIMER ANTICPO DE ISLR | D49: 1 | E49: =IFERROR(VLOOKUP(D:D,'AUXILIAR DE CLASIFICACION'!A:B,2,FALSE),"") -> Impuestos Seniat | F49: 46766 | G49: =IFERROR(F49/H49,0) -> 61.184013 | H49: 764.35
A50: 46246 | B50: =TEXT(Tabla1[[#This Row],[Fecha ]],"MMMM") -> August | C50: RETENCIONDE IVA | D50: 1 | E50: =IFERROR(VLOOKUP(D:D,'AUXILIAR DE CLASIFICACION'!A:B,2,FALSE),"") -> Impuestos Seniat | F50: 721339 | G50: =IFERROR(F50/H50,0) -> 943.72866 | H50: 764.35
A51: 46246 | B51: =TEXT(Tabla1[[#This Row],[Fecha ]],"MMMM") -> August | C51: RETENCION DE ISLR | D51: 1 | E51: =IFERROR(VLOOKUP(D:D,'AUXILIAR DE CLASIFICACION'!A:B,2,FALSE),"") -> Impuestos Seniat | F51: 5518 | G51: =IFERROR(F51/H51,0) -> 7.2192059 | H51: 764.35
A52: 46254 | B52: =TEXT(Tabla1[[#This Row],[Fecha ]],"MMMM") -> August | C52: IMPUESTO DECLARACION PAGO DE PENSIONES | D52: 1 | E52: =IFERROR(VLOOKUP(D:D,'AUXILIAR DE CLASIFICACION'!A:B,2,FALSE),"") -> Impuestos Seniat | F52: 145250.17 | G52: =IFERROR(F52/H52,0) -> 186.83616 | H52: 777.42
A53: 46254 | B53: =TEXT(Tabla1[[#This Row],[Fecha ]],"MMMM") -> August | C53: PAGO ALQUILER 15/7/26 AL 15/8/26 | D53: 6 | E53: =IFERROR(VLOOKUP(D:D,'AUXILIAR DE CLASIFICACION'!A:B,2,FALSE),"") -> Alquileres | F53: 2040367.5 | G53: =IFERROR(F53/H53,0) -> 2250 | H53: 906.83
A54: 46254 | B54: =TEXT(Tabla1[[#This Row],[Fecha ]],"MMMM") -> August | C54: IMPUESTO ANTICIPO DE ISLR FORMA 99044 | D54: 1 | E54: =IFERROR(VLOOKUP(D:D,'AUXILIAR DE CLASIFICACION'!A:B,2,FALSE),"") -> Impuestos Seniat | F54: 44789.02 | G54: =IFERROR(F54/H54,0) -> 57.612385 | H54: 777.42
A55: 46254 | B55: =TEXT(Tabla1[[#This Row],[Fecha ]],"MMMM") -> August | C55: IMPUESTO RETENCION IVA FORMA 99035 | D55: 1 | E55: =IFERROR(VLOOKUP(D:D,'AUXILIAR DE CLASIFICACION'!A:B,2,FALSE),"") -> Impuestos Seniat | F55: 261758.08 | G55: =IFERROR(F55/H55,0) -> 336.70099 | H55: 777.42
A56: 46254 | B56: =TEXT(Tabla1[[#This Row],[Fecha ]],"MMMM") -> August | C56: PAGO HECTOR PUBLICIDAD DEL 15/7/26 AL 15/8/26 | D56: 4 | E56: =IFERROR(VLOOKUP(D:D,'AUXILIAR DE CLASIFICACION'!A:B,2,FALSE),"") -> Servicios | F56: 208570.9 | G56: =IFERROR(F56/H56,0) -> 230 | H56: 906.83
A57: 46255 | B57: =TEXT(Tabla1[[#This Row],[Fecha ]],"MMMM") -> August | C57: CUOTA 3/3 CESTA PARA ALMACEN | D57: 9 | E57: =IFERROR(VLOOKUP(D:D,'AUXILIAR DE CLASIFICACION'!A:B,2,FALSE),"") -> Gastos Extraordinarios | F57: 50117.1 | G57: =IFERROR(F57/H57,0) -> 55 | H57: 911.22
A58: 46256 | B58: =TEXT(Tabla1[[#This Row],[Fecha ]],"MMMM") -> August | C58: TRABAJO Y DELIGENCIAS DANIEL ZABALA | D58: 9 | E58: =IFERROR(VLOOKUP(D:D,'AUXILIAR DE CLASIFICACION'!A:B,2,FALSE),"") -> Gastos Extraordinarios | F58: 350977.5 | G58: =IFERROR(F58/H58,0) -> 450 | H58: 779.95
A59: 46258 | B59: =TEXT(Tabla1[[#This Row],[Fecha ]],"MMMM") -> August | C59: GASOLINA PANEL DANIEL RODRIGUEZ | D59: 12 | E59: =IFERROR(VLOOKUP(D:D,'AUXILIAR DE CLASIFICACION'!A:B,2,FALSE),"") -> Mantenimiento Flota | F59: 15693.2 | G59: =IFERROR(F59/H59,0) -> 20 | H59: 784.66
A60: 46258 | B60: =TEXT(Tabla1[[#This Row],[Fecha ]],"MMMM") -> August | C60: PAGO DE FACTURA IMA JULIO 2026 | D60: 2 | E60: =IFERROR(VLOOKUP(D:D,'AUXILIAR DE CLASIFICACION'!A:B,2,FALSE),"") -> Impuestos Municipales | F60: 34275.74 | G60: 43.508621 | H60: 757.54
A61: 46259 | B61: =TEXT(Tabla1[[#This Row],[Fecha ]],"MMMM") -> August | C61: PAGO DE IMPUESTO ALCALDIA JULIO 26 | D61: 2 | E61: =IFERROR(VLOOKUP(D:D,'AUXILIAR DE CLASIFICACION'!A:B,2,FALSE),"") -> Impuestos Municipales | F61: 234528.76 | G61: =IFERROR(F61/H61,0) -> 298.73611 | H61: 785.07
A62: 46259 | B62: =TEXT(Tabla1[[#This Row],[Fecha ]],"MMMM") -> August | C62: COMISONES DE VENTAS SEMANA DEL 17/8/26 AL 22/8 | D62: 8 | E62: =IFERROR(VLOOKUP(D:D,'AUXILIAR DE CLASIFICACION'!A:B,2,FALSE),"") -> Comisiones por venta | F62: 107265.78 | G62: =IFERROR(F62/H62,0) -> 136.63212 | H62: 785.07
A63: 46259 | B63: =TEXT(Tabla1[[#This Row],[Fecha ]],"MMMM") -> August | C63: COMPRA DE PAPELERIA | D63: 9 | E63: =IFERROR(VLOOKUP(D:D,'AUXILIAR DE CLASIFICACION'!A:B,2,FALSE),"") -> Gastos Extraordinarios | F63: 22291.82 | G63: =IFERROR(F63/H63,0) -> 28.394691 | H63: 785.07
A64: 46260 | B64: =TEXT(Tabla1[[#This Row],[Fecha ]],"MMMM") -> August | C64: PAGO FAOV FORMA 80001 AGOSTO 2026 | D64: 3 | E64: =IFERROR(VLOOKUP(D:D,'AUXILIAR DE CLASIFICACION'!A:B,2,FALSE),"") -> Parafiscales | F64: 17264.64 | G64: =IFERROR(F64/H64,0) -> 22.002702 | H64: 784.66
A65: 46260 | B65: =TEXT(Tabla1[[#This Row],[Fecha ]],"MMMM") -> August | C65: REPARACION DE RADIADOR PANEL | D65: 12 | E65: =IFERROR(VLOOKUP(D:D,'AUXILIAR DE CLASIFICACION'!A:B,2,FALSE),"") -> Mantenimiento Flota | F65: 27575 | G65: =IFERROR(F65/H65,0) -> 35.014984 | H65: 787.52
A66: 46261 | B66: =TEXT(Tabla1[[#This Row],[Fecha ]],"MMMM") -> August | C66: COPRA DE PINZAS Y MARCADORES | D66: 9 | E66: =IFERROR(VLOOKUP(D:D,'AUXILIAR DE CLASIFICACION'!A:B,2,FALSE),"") -> Gastos Extraordinarios | F66: 7355.23 | G66: =IFERROR(F66/H66,0) -> 9.294887 | H66: 791.32
A67: 46261 | B67: =TEXT(Tabla1[[#This Row],[Fecha ]],"MMMM") -> August | C67: REPUESTO PARA AMBIENTADORES DE TIENDA | D67: 9 | E67: =IFERROR(VLOOKUP(D:D,'AUXILIAR DE CLASIFICACION'!A:B,2,FALSE),"") -> Gastos Extraordinarios | F67: 12242.06 | G67: =IFERROR(F67/H67,0) -> 15.470429 | H67: 791.32
A68: 46261 | B68: =TEXT(Tabla1[[#This Row],[Fecha ]],"MMMM") -> August | C68: CAMBIO DE ACEITE DE LA PANEL DANIEL ZABALA | D68: 12 | E68: =IFERROR(VLOOKUP(D:D,'AUXILIAR DE CLASIFICACION'!A:B,2,FALSE),"") -> Mantenimiento Flota | F68: 121863.28 | G68: =IFERROR(F68/H68,0) -> 154 | H68: 791.32
A69: 46262 | B69: =TEXT(Tabla1[[#This Row],[Fecha ]],"MMMM") -> August | C69: HONORARIOS JULIO 2026 SABRINA AULAR | D69: 4 | E69: =IFERROR(VLOOKUP(D:D,'AUXILIAR DE CLASIFICACION'!A:B,2,FALSE),"") -> Servicios | F69: 114741.4 | G69: =IFERROR(F69/H69,0) -> 145 | H69: 791.32
A70: 46262 | B70: =TEXT(Tabla1[[#This Row],[Fecha ]],"MMMM") -> August | C70: PAGO DE NOMINA SEGUNDA QUINCENA AGOSTO 30/8/26 | D70: 7 | E70: =IFERROR(VLOOKUP(D:D,'AUXILIAR DE CLASIFICACION'!A:B,2,FALSE),"") -> Nomina y Pasivos Laborales | F70: 1429410 | G70: =IFERROR(F70/H70,0) -> 1805.5629 | H70: 791.67
A71: 46262 | B71: =TEXT(Tabla1[[#This Row],[Fecha ]],"MMMM") -> August | C71: PAGO DE IVSS JULIO 2026 | D71: 3 | E71: =IFERROR(VLOOKUP(D:D,'AUXILIAR DE CLASIFICACION'!A:B,2,FALSE),"") -> Parafiscales | F71: 35.4 | G71: =IFERROR(F71/H71,0) -> 0.044951239 | H71: 787.52
A72: 46262 | B72: =TEXT(Tabla1[[#This Row],[Fecha ]],"MMMM") -> August | C72: CESTA AGRICOLA COLOR NEGRO | D72: 9 | E72: =IFERROR(VLOOKUP(D:D,'AUXILIAR DE CLASIFICACION'!A:B,2,FALSE),"") -> Gastos Extraordinarios | F72: 26734.52 | G72: =IFERROR(F72/H72,0) -> 29 | H72: 921.88
... A83: 46265 | B83: =TEXT(Tabla1[[#This Row],[Fecha ]],"MMMM") -> August | C83: COMISIONES BANCARIAS BANCO DE VENZUELA | D83: 9 | E83: =IFERROR(VLOOKUP(D:D,'AUXILIAR DE CLASIFICACION'!A:B,2,FALSE),"") -> Gastos Extraordinarios | F83: 30016.4 | G83: =IFERROR(F83/H83,0) -> 37.756953 | H83: 794.99
A84: 46241 | B84: =TEXT(Tabla1[[#This Row],[Fecha ]],"MMMM") -> August | C84: gastos operativos | D84: 9 | E84: =IFERROR(VLOOKUP(D:D,'AUXILIAR DE CLASIFICACION'!A:B,2,FALSE),"") -> Gastos Extraordinarios | G84: 93.224138
A85: 46246 | B85: =TEXT(Tabla1[[#This Row],[Fecha ]],"MMMM") -> August | C85: gastos operativos | D85: 9 | E85: =IFERROR(VLOOKUP(D:D,'AUXILIAR DE CLASIFICACION'!A:B,2,FALSE),"") -> Gastos Extraordinarios | G85: 23.275862
A86: 46259 | B86: =TEXT(Tabla1[[#This Row],[Fecha ]],"MMMM") -> August | C86: gastos operativos | D86: 9 | E86: =IFERROR(VLOOKUP(D:D,'AUXILIAR DE CLASIFICACION'!A:B,2,FALSE),"") -> Gastos Extraordinarios | G86: 57.663793
G87: =SUBTOTAL(109,Tabla1[Monto $]) -> 16161.214

Sheet AUXILIAR DE CLASIFICACION
A1: ID | B1: TIPO DE GASTO | E1: PRESUPUESTO
A2: 1 | B2: Impuestos Seniat | E2: Impuestos Seniat | F2: 1500
A3: 2 | B3: Impuestos Municipales | E3: Impuestos Municipales | F3: 500
A4: 3 | B4: Parafiscales | E4: Parafiscales | F4: 150
A5: 4 | B5: Servicios | E5: Servicios | F5: 2500
A6: 5 | B6: Gastos Operativos y Mantenimiento | E6: Gastos Operativos y Mantenimiento | F6: 500
A7: 6 | B7: Alquileres | E7: Alquileres | F7: 4000
A8: 7 | B8: Nomina y Pasivos Laborales | E8: Nomina y Pasivos Laborales | F8: 4500
A9: 8 | B9: Comisiones por venta | E9: Comisiones por venta | F9: 2000
A10: 9 | B10: Gastos Extraordinarios | E10: Gastos Extraordinarios | F10: 1500
A11: 10 | B11: Compras de Bienes | E11: Compras de Bienes | F11: 1000
A12: 11 | B12: Retiros de Accionista | E12: Retiros de Accionista | F12: 2500
A13: 12 | B13: Mantenimiento Flota | E13: Mantenimiento Flota

Sheet ALERTA
B6: ID | C6: PRESUPUESTO | D6: MONTO MAXIMO | E6: MONTO GASTADO | F6: RESTANTE | G6: STATUS
B7: 1 | C7: Impuestos Seniat | D7: 1500 | E7: =IFERROR(VLOOKUP(B:B,'TABLA DINAMICA ACTUALIZAR '!A:D,2,FALSE),0) -> 1593.2814 | F7: =D7-E7 -> -93.28141 | G7: =IF(F:F<=50,"ALERTA","APTO") -> ALERTA | I7: MONTO PRESUPUESTO | J7: GASTO TOTAL | K7: PORCENTAJE
B8: 2 | C8: Impuestos Municipales | D8: 500 | E8: =IFERROR(VLOOKUP(B:B,'TABLA DINAMICA ACTUALIZAR '!A:D,2,FALSE),0) -> 345.68339 | F8: =D8-E8 -> 154.31661 | G8: =IF(F:F<=50,"ALERTA","APTO") -> APTO | I8: =D19 -> 14000 | J8: =E19 -> 16161.214 | K8: =J8/I8*100 -> 115.43724
B9: 3 | C9: Parafiscales | D9: 100 | E9: =IFERROR(VLOOKUP(B:B,'TABLA DINAMICA ACTUALIZAR '!A:D,2,FALSE),0) -> 44.050495 | F9: =IFERROR(D9-E9,"") -> 55.949505 | G9: =IF(F:F<=50,"ALERTA","APTO") -> APTO
B10: 4 | C10: Servicios | D10: 1000 | E10: =IFERROR(VLOOKUP(B:B,'TABLA DINAMICA ACTUALIZAR '!A:D,2,FALSE),0) -> 1638.712 | F10: =IFERROR(D10-E10,"") -> -638.71197 | G10: =IF(F:F<=50,"ALERTA","APTO") -> ALERTA
B11: 5 | C11: Gastos Operativos y Mantenimiento | D11: 500 | E11: =IFERROR(VLOOKUP(B:B,'TABLA DINAMICA ACTUALIZAR '!A:D,2,FALSE),0) -> 0 | F11: =IFERROR(D11-E11,"") -> 500 | G11: =IF(F:F<=50,"ALERTA","APTO") -> APTO
B12: 6 | C12: Alquileres | D12: 2250 | E12: =IFERROR(VLOOKUP(B:B,'TABLA DINAMICA ACTUALIZAR '!A:D,2,FALSE),0) -> 2250 | F12: =IFERROR(D12-E12,"") -> 0 | G12: =IF(F:F<=50,"ALERTA","APTO") -> ALERTA
B13: 7 | C13: Nomina y Pasivos Laborales | D13: 4500 | E13: =IFERROR(VLOOKUP(B:B,'TABLA DINAMICA ACTUALIZAR '!A:D,2,FALSE),0) -> 3450.1121 | F13: =IFERROR(D13-E13,"") -> 1049.8879 | G13: =IF(F:F<=50,"ALERTA","APTO") -> APTO
B14: 8 | C14: Comisiones por venta | D14: 1200 | E14: =IFERROR(VLOOKUP(B:B,'TABLA DINAMICA ACTUALIZAR '!A:D,2,FALSE),0) -> 789.51209 | F14: =IFERROR(D14-E14,"") -> 410.48791 | G14: =IF(F:F<=50,"ALERTA","APTO") -> APTO
B15: 9 | C15: Gastos Extraordinarios | D15: 1000 | E15: =IFERROR(VLOOKUP(B:B,'TABLA DINAMICA ACTUALIZAR '!A:D,2,FALSE),0) -> 3739.5512 | F15: =IFERROR(D15-E15,"") -> -2739.5512 | G15: =IF(F:F<=50,"ALERTA","APTO") -> ALERTA
B16: 10 | C16: Compras de Bienes | D16: 500 | E16: =IFERROR(VLOOKUP(B:B,'TABLA DINAMICA ACTUALIZAR '!A:D,2,FALSE),0) -> 0 | F16: =IFERROR(D16-E16,"") -> 500 | G16: =IF(F:F<=50,"ALERTA","APTO") -> APTO
B17: 11 | C17: Retiros de Accionista | D17: 750 | E17: =IFERROR(VLOOKUP(B:B,'TABLA DINAMICA ACTUALIZAR '!A:D,2,FALSE),0) -> 2000 | F17: =IFERROR(D17-E17,"") -> -1250 | G17: =IF(F:F<=50,"ALERTA","APTO") -> ALERTA
B18: 12 | C18: Mantenimiento Flota | D18: 200 | E18: =IFERROR(VLOOKUP(B:B,'TABLA DINAMICA ACTUALIZAR '!A:D,2,FALSE),0) -> 310.31111 | F18: =IFERROR(D18-E18,"") -> -110.31111 | G18: =IF(F:F<=50,"ALERTA","APTO") -> ALERTA
D19: =SUM(D7:D18) -> 14000 | E19: =SUM(E7:E18) -> 16161.214 | F19: =+D19-E19 -> -2161.2138 | G19: =IF(F:F<=50,"ALERTA","APTO") -> ALERTA

Sheet TABLA DINAMICA ACTUALIZAR 
A3: Suma de Monto $ | B3: Etiquetas de columna
A4: Etiquetas de fila | B4: August | C4: Total general | D4: % participacion
A5: 1 | B5: 1593.2814 | C5: 1593.2814 | D5: =+B5/B$15 -> 0.098586742
A6: 2 | B6: 345.68339 | C6: 345.68339 | D6: =+B6/B$15 -> 0.021389692
A7: 3 | B7: 44.050495 | C7: 44.050495 | D7: =+B7/B$15 -> 0.0027256922
A8: 4 | B8: 1638.712 | C8: 1638.712 | D8: =+B8/B$15 -> 0.10139783
A9: 6 | B9: 2250 | C9: 2250 | D9: =+B9/B$15 -> 0.13922222
A10: 7 | B10: 3450.1121 | C10: 3450.1121 | D10: =+B10/B$15 -> 0.213481
A11: 8 | B11: 789.51209 | C11: 789.51209 | D11: =+B11/B$15 -> 0.048852277
A12: 9 | B12: 3739.5512 | C12: 3739.5512 | D12: =+B12/B$15 -> 0.23139049
A13: 11 | B13: 2000 | C13: 2000 | D13: =+B13/B$15 -> 0.12375308
A14: 12 | B14: 310.31111 | C14: 310.31111 | D14: =+B14/B$15 -> 0.019200978
A15: Total general | B15: 16161.214 | C15: 16161.214 | D15: =+B15/B$15 -> 1
